tests/__init__.py
tests/run_me.py
tests/test_config_utils.py
tests/test_os_utils.py
tests/test_pio.py
tests/test_threadutils.py
tests/test_time_utils.py
thompcoUtils/__init__.py
thompcoUtils/cell_phone.py
thompcoUtils/config_utils.py
thompcoUtils/cron_time.py
thompcoUtils/db_utils.py
thompcoUtils/email_utils.py
thompcoUtils/file_utils.py
thompcoUtils/genericArgs.py
thompcoUtils/genericConfig.py
thompcoUtils/html_utils.py
thompcoUtils/log_utils.py
thompcoUtils/math_utils.py
thompcoUtils/os_utils.py
thompcoUtils/peak_time.py
thompcoUtils/pio.py
thompcoUtils/pio_exception.py
thompcoUtils/security_utils.py
thompcoUtils/setup.py
thompcoUtils/string_utils.py
thompcoUtils/test_utils.py
thompcoUtils/threading_utils.py
thompcoUtils/time_utils.py
thompcoUtils/units.py
thompcoUtils/version.py
thompcoUtils/web_utils.py
thompcoutils-2.2.5.dist-info/LICENSE
thompcoutils-2.2.5.dist-info/METADATA
thompcoutils-2.2.5.dist-info/WHEEL
thompcoutils-2.2.5.dist-info/top_level.txt
thompcoutils-2.2.5.dist-info/RECORD
