Metadata-Version: 2.1
Name: thompcoutils
Version: 2.2.5
Summary: Another collection of utilities
Home-page: https://github.com/pypa/sampleproject
Author: Jordan Thompson
Author-email: Jordan@ThompCo.com
License: UNKNOWN
Platform: UNKNOWN
Classifier: Programming Language :: Python :: 3
Classifier: License :: OSI Approved :: MIT License
Classifier: Operating System :: OS Independent
License-File: LICENSE
Requires-Dist: netifaces
Requires-Dist: psutil
Requires-Dist: python-dateutil
